README.rst
setup.py
pyopenbr/__init__.py
pyopenbr.egg-info/PKG-INFO
pyopenbr.egg-info/SOURCES.txt
pyopenbr.egg-info/dependency_links.txt
pyopenbr.egg-info/not-zip-safe
pyopenbr.egg-info/top_level.txt