Metadata-Version: 1.1
Name: pyopenbr
Version: 0.2
Summary: Improved Python Wrapper for the OpenBR Command-line Tool.
Home-page: https://github.com/ant0nisk/pyopenbr
Author: Antonis Katzourakis
Author-email: antonis.katzourakis@gmail.com
License: Apache License, Version 2.0
Keywords: open biometrics openbr face recognition
Platform: UNKNOWN
Classifier: Development Status :: 3 - Alpha
Classifier: License :: OSI Approved :: Apache Software License
Classifier: Programming Language :: Python
Classifier: Topic :: Text Processing :: Linguistic
